otomkdir/__init__.py
otomkdir/otomkdir.py
otomkdir-0.1.0.dist-info/LICENSE.txt
otomkdir-0.1.0.dist-info/METADATA
otomkdir-0.1.0.dist-info/WHEEL
otomkdir-0.1.0.dist-info/top_level.txt
otomkdir-0.1.0.dist-info/RECORD
